LICENSE
MANIFEST.in
README.md
README.rst
setup.py
tox.ini
j2cli_3/__init__.py
j2cli_3/cli.py
j2cli_3/context.py
j2cli_3.egg-info/PKG-INFO
j2cli_3.egg-info/SOURCES.txt
j2cli_3.egg-info/dependency_links.txt
j2cli_3.egg-info/entry_points.txt
j2cli_3.egg-info/not-zip-safe
j2cli_3.egg-info/requires.txt
j2cli_3.egg-info/top_level.txt
j2cli_3/extras/__init__.py
j2cli_3/extras/filters.py