Metadata-Version: 2.1
Name: j2cli-3
Version: 0.0.1
Summary: Command-line interface to Jinja2 for templating in shell scripts.
Home-page: https://github.com/leumas95/j2cli_3
Author: Samuel Windall
Author-email: samuel.windall@gmail.com
License: BSD
Keywords: Jinja2,templating,command-line,CLI
Platform: any
Classifier: Development Status :: 5 - Production/Stable
Classifier: Intended Audience :: Developers
Classifier: Intended Audience :: System Administrators
Classifier: Operating System :: OS Independent
Classifier: Topic :: Software Development
Classifier: Natural Language :: English
Classifier: Programming Language :: Python :: 3
Provides-Extra: yaml
